changelog_tools/__init__.py
changelog_tools/__main__.py
changelog_tools/changelog_tools.py
changelog_tools/changelog_helpers/helpers.py
changelog_tools/changelog_helpers/summarize.py
changelog_tools-0.4.0.dist-info/licenses/LICENSE
changelog_tools-0.4.0.dist-info/METADATA
changelog_tools-0.4.0.dist-info/WHEEL
changelog_tools-0.4.0.dist-info/top_level.txt
changelog_tools-0.4.0.dist-info/RECORD
