Metadata-Version: 2.4
Name: changelog_tools
Version: 0.4.0
Summary: This project provides tools to manage changelog files.
Author-email: Sigilence Technologies <contact@sigilence.com>
License: FreeBSD License
Project-URL: Our Website, https://www.sigilence-technologies.com/
Classifier: Programming Language :: Python :: 3.10
Classifier: Programming Language :: Python :: 3.11
Classifier: Programming Language :: Python :: 3.12
Classifier: Operating System :: OS Independent
Classifier: Development Status :: 5 - Production/Stable
Classifier: Intended Audience :: Developers
Requires-Python: >=3.10
License-File: LICENSE
Dynamic: license-file
